PyShiftAE/PSCAE.pyd
PyShiftAE/PSCAE.pyi
PyShiftAE/PyShiftAE.aex
PyShiftAE/__init__.py
PyShiftAE/extension_utils.py
PyShiftAE-1.0.1.dist-info/METADATA
PyShiftAE-1.0.1.dist-info/WHEEL
PyShiftAE-1.0.1.dist-info/top_level.txt
PyShiftAE-1.0.1.dist-info/RECORD
