Metadata-Version: 2.1
Name: PyShiftAE
Version: 1.0.1
Summary: Python for After Effects
Author: Trenton Flanagan
Classifier: Programming Language :: Python :: 3
Classifier: License :: OSI Approved :: MIT License
Requires-Python: >=3.5
